COPYING
README.rst
setup.py
bhexpress/__init__.py
bhexpress.egg-info/PKG-INFO
bhexpress.egg-info/SOURCES.txt
bhexpress.egg-info/dependency_links.txt
bhexpress.egg-info/requires.txt
bhexpress.egg-info/top_level.txt
bhexpress/api_client/__init__.py
bhexpress/api_client/bhe/__init__.py
bhexpress/api_client/bhe/boletas.py
bhexpress/api_client/bhe/receptores.py
bhexpress/api_client/bhe/servicios.py